{"Version":96,"Data":[{"Id":1,"Name":"CardName1","Resource":"leibniz","Rare":3,"EffectId":1},{"Id":2,"Name":"CardName2","Resource":"edison","Rare":5,"EffectId":1},{"Id":3,"Name":"CardName3","Resource":"einstein","Rare":5,"EffectId":1},{"Id":4,"Name":"CardName4","Resource":"newton","Rare":4,"EffectId":1},{"Id":5,"Name":"CardName5","Resource":"aristoteles","Rare":3,"EffectId":1},{"Id":6,"Name":"CardName6","Resource":"copernicus","Rare":3,"EffectId":1},{"Id":7,"Name":"CardName7","Resource":"galileo","Rare":4,"EffectId":1},{"Id":8,"Name":"CardName8","Resource":"hippocrates","Rare":3,"EffectId":1},{"Id":9,"Name":"CardName9","Resource":"platon","Rare":4,"EffectId":1},{"Id":10,"Name":"CardName10","Resource":"wright_brothers","Rare":4,"EffectId":1},{"Id":11,"Name":"CardName11","Resource":"pythagoras","Rare":5,"EffectId":1},{"Id":12,"Name":"CardName12","Resource":"nikola_tesla","Rare":5,"EffectId":1},{"Id":13,"Name":"CardName13","Resource":"graham_bell","Rare":4,"EffectId":1},{"Id":14,"Name":"CardName14","Resource":"gauss","Rare":3,"EffectId":1},{"Id":15,"Name":"CardName15","Resource":"fleming","Rare":3,"EffectId":1},{"Id":16,"Name":"CardName16","Resource":"koumei","Rare":4,"EffectId":1},{"Id":17,"Name":"CardName17","Resource":"taresu","Rare":3,"EffectId":1},{"Id":18,"Name":"CardName18","Resource":"faraday","Rare":3,"EffectId":1},{"Id":19,"Name":"CardName19","Resource":"ampere","Rare":3,"EffectId":1},{"Id":20,"Name":"CardName20","Resource":"socrates","Rare":3,"EffectId":1},{"Id":21,"Name":"","Resource":"","Rare":0,"EffectId":0},{"Id":22,"Name":"","Resource":"","Rare":0,"EffectId":0},{"Id":23,"Name":"","Resource":"","Rare":0,"EffectId":0},{"Id":24,"Name":"","Resource":"","Rare":0,"EffectId":0},{"Id":25,"Name":"","Resource":"","Rare":0,"EffectId":0},{"Id":26,"Name":"","Resource":"","Rare":0,"EffectId":0},{"Id":27,"Name":"","Resource":"","Rare":0,"EffectId":0},{"Id":28,"Name":"","Resource":"","Rare":0,"EffectId":0}]}